pyAutoSummarizer/__init__.py
pyAutoSummarizer/base/__init__.py
pyAutoSummarizer/base/psr.py
pyAutoSummarizer/base/stws/Stopwords-Arabic.txt
pyAutoSummarizer/base/stws/Stopwords-Bengali.txt
pyAutoSummarizer/base/stws/Stopwords-Bulgarian.txt
pyAutoSummarizer/base/stws/Stopwords-Chinese.txt
pyAutoSummarizer/base/stws/Stopwords-Czech.txt
pyAutoSummarizer/base/stws/Stopwords-English.txt
pyAutoSummarizer/base/stws/Stopwords-Finnish.txt
pyAutoSummarizer/base/stws/Stopwords-French.txt
pyAutoSummarizer/base/stws/Stopwords-German.txt
pyAutoSummarizer/base/stws/Stopwords-Greek.txt
pyAutoSummarizer/base/stws/Stopwords-Hebrew.txt
pyAutoSummarizer/base/stws/Stopwords-Hindi.txt
pyAutoSummarizer/base/stws/Stopwords-Hungarian.txt
pyAutoSummarizer/base/stws/Stopwords-Italian.txt
pyAutoSummarizer/base/stws/Stopwords-Japanese.txt
pyAutoSummarizer/base/stws/Stopwords-Korean.txt
pyAutoSummarizer/base/stws/Stopwords-Marathi.txt
pyAutoSummarizer/base/stws/Stopwords-Persian.txt
pyAutoSummarizer/base/stws/Stopwords-Polish.txt
pyAutoSummarizer/base/stws/Stopwords-Portuguese-br.txt
pyAutoSummarizer/base/stws/Stopwords-Romanian.txt
pyAutoSummarizer/base/stws/Stopwords-Russian.txt
pyAutoSummarizer/base/stws/Stopwords-Slovak.txt
pyAutoSummarizer/base/stws/Stopwords-Spanish.txt
pyAutoSummarizer/base/stws/Stopwords-Swedish.txt
pyAutoSummarizer/base/stws/Stopwords-Thai.txt
pyAutoSummarizer/base/stws/Stopwords-Ukrainian.txt
pyAutoSummarizer/base/stws/__init__.py
pyAutoSummarizer-1.1.8.dist-info/LICENSE
pyAutoSummarizer-1.1.8.dist-info/METADATA
pyAutoSummarizer-1.1.8.dist-info/WHEEL
pyAutoSummarizer-1.1.8.dist-info/top_level.txt
pyAutoSummarizer-1.1.8.dist-info/zip-safe
pyAutoSummarizer-1.1.8.dist-info/RECORD
