Metadata-Version: 2.1
Name: pyAutoSummarizer
Version: 1.1.8
Summary: An Extractive and Abstractive Summarization Library Powered with Artificial Intelligence
Home-page: https://github.com/Valdecy/pyAutoSummarizer
Author: Valdecy Pereira
Author-email: valdecy.pereira@gmail.com
License: GNU
License-File: LICENSE
Requires-Dist: chardet
Requires-Dist: numpy
Requires-Dist: llmx
Requires-Dist: regex
Requires-Dist: scikit-learn
Requires-Dist: sentence-transformers
Requires-Dist: openai
Requires-Dist: transformers
